{
  "metadata": {
    "language": "zh",
    "language_name": "Chinese",
    "glossary_type": "法律术语词典",
    "version": "1.0.0",
    "created": "2025-11-24",
    "description": "中国法律术语词汇表",
    "sources": [
      "中华人民共和国民法典",
      "中华人民共和国刑法",
      "中华人民共和国公司法",
      "全国科学技术名词审定委员会"
    ],
    "total_terms": 210
  },
  "categories": {
    "contract_law": [
      {"zh": "合同", "en": "contract"},
      {"zh": "要约", "en": "offer"},
      {"zh": "要约邀请", "en": "invitation to offer"},
      {"zh": "承诺", "en": "acceptance"},
      {"zh": "违约", "en": "breach of contract"},
      {"zh": "违约责任", "en": "liability for breach"},
      {"zh": "格式条款", "en": "standard terms"},
      {"zh": "定金", "en": "deposit"},
      {"zh": "违约金", "en": "liquidated damages"},
      {"zh": "损害赔偿", "en": "damages"},
      {"zh": "合同解除", "en": "termination"},
      {"zh": "标的", "en": "subject matter"},
      {"zh": "先履行抗辩权", "en": "defense of prior performance"},
      {"zh": "同时履行抗辩权", "en": "defense of simultaneous performance"},
      {"zh": "不安抗辩权", "en": "defense of insecurity"}
    ],
    "litigation": [
      {"zh": "原告", "en": "plaintiff"},
      {"zh": "被告", "en": "defendant"},
      {"zh": "被告人", "en": "accused (criminal)"},
      {"zh": "起诉", "en": "sue"},
      {"zh": "上诉", "en": "appeal"},
      {"zh": "上诉人", "en": "appellant"},
      {"zh": "被上诉人", "en": "appellee"},
      {"zh": "申诉", "en": "petition for retrial"},
      {"zh": "抗诉", "en": "protest"},
      {"zh": "反诉", "en": "counterclaim"},
      {"zh": "当事人", "en": "party"},
      {"zh": "第三人", "en": "third party"},
      {"zh": "诉讼代理人", "en": "litigation agent"},
      {"zh": "管辖", "en": "jurisdiction"},
      {"zh": "举证责任", "en": "burden of proof"},
      {"zh": "证据", "en": "evidence"},
      {"zh": "庭审", "en": "trial"},
      {"zh": "缺席判决", "en": "default judgment"},
      {"zh": "调解", "en": "mediation"},
      {"zh": "和解", "en": "settlement"},
      {"zh": "执行", "en": "enforcement"},
      {"zh": "再审", "en": "retrial"}
    ],
    "corporate_law": [
      {"zh": "有限责任公司", "en": "limited liability company"},
      {"zh": "股份有限公司", "en": "joint stock company"},
      {"zh": "股东", "en": "shareholder"},
      {"zh": "股东会", "en": "shareholders' meeting"},
      {"zh": "股东大会", "en": "general meeting"},
      {"zh": "董事", "en": "director"},
      {"zh": "董事会", "en": "board of directors"},
      {"zh": "董事长", "en": "chairman"},
      {"zh": "监事", "en": "supervisor"},
      {"zh": "监事会", "en": "board of supervisors"},
      {"zh": "高级管理人员", "en": "senior management"},
      {"zh": "法定代表人", "en": "legal representative"},
      {"zh": "注册资本", "en": "registered capital"},
      {"zh": "实收资本", "en": "paid-in capital"},
      {"zh": "股权", "en": "equity"},
      {"zh": "股权转让", "en": "equity transfer"},
      {"zh": "控股股东", "en": "controlling shareholder"},
      {"zh": "实际控制人", "en": "actual controller"},
      {"zh": "关联交易", "en": "related party transaction"},
      {"zh": "忠实义务", "en": "duty of loyalty"},
      {"zh": "勤勉义务", "en": "duty of diligence"},
      {"zh": "公司章程", "en": "articles of association"},
      {"zh": "清算", "en": "liquidation"},
      {"zh": "破产", "en": "bankruptcy"}
    ],
    "criminal_law": [
      {"zh": "犯罪", "en": "crime"},
      {"zh": "罪名", "en": "criminal charge"},
      {"zh": "刑罚", "en": "punishment"},
      {"zh": "主刑", "en": "principal punishment"},
      {"zh": "附加刑", "en": "supplementary punishment"},
      {"zh": "死刑", "en": "death penalty"},
      {"zh": "无期徒刑", "en": "life imprisonment"},
      {"zh": "有期徒刑", "en": "fixed-term imprisonment"},
      {"zh": "拘役", "en": "criminal detention"},
      {"zh": "管制", "en": "public surveillance"},
      {"zh": "罚金", "en": "fine"},
      {"zh": "犯罪构成", "en": "elements of crime"},
      {"zh": "故意犯罪", "en": "intentional crime"},
      {"zh": "过失犯罪", "en": "negligent crime"},
      {"zh": "正当防卫", "en": "justifiable defense"},
      {"zh": "紧急避险", "en": "emergency rescue"},
      {"zh": "犯罪未遂", "en": "attempted crime"},
      {"zh": "共同犯罪", "en": "joint crime"},
      {"zh": "主犯", "en": "principal offender"},
      {"zh": "从犯", "en": "accessory"},
      {"zh": "累犯", "en": "recidivist"},
      {"zh": "自首", "en": "voluntary surrender"},
      {"zh": "立功", "en": "meritorious service"}
    ],
    "property_law": [
      {"zh": "物权", "en": "property right"},
      {"zh": "所有权", "en": "ownership"},
      {"zh": "用益物权", "en": "usufruct"},
      {"zh": "担保物权", "en": "security interest"},
      {"zh": "抵押", "en": "mortgage"},
      {"zh": "抵押权", "en": "mortgage right"},
      {"zh": "质押", "en": "pledge"},
      {"zh": "质权", "en": "pledge right"},
      {"zh": "留置权", "en": "right of lien"},
      {"zh": "占有", "en": "possession"},
      {"zh": "善意取得", "en": "bona fide acquisition"},
      {"zh": "不动产", "en": "immovable property"},
      {"zh": "动产", "en": "movable property"},
      {"zh": "建设用地使用权", "en": "right to use land for construction"},
      {"zh": "宅基地使用权", "en": "right to use homestead"},
      {"zh": "土地承包经营权", "en": "right to contracted management of land"},
      {"zh": "地役权", "en": "easement"}
    ],
    "intellectual_property": [
      {"zh": "知识产权", "en": "intellectual property"},
      {"zh": "专利", "en": "patent"},
      {"zh": "专利权", "en": "patent right"},
      {"zh": "发明专利", "en": "invention patent"},
      {"zh": "实用新型专利", "en": "utility model patent"},
      {"zh": "外观设计专利", "en": "design patent"},
      {"zh": "商标", "en": "trademark"},
      {"zh": "商标权", "en": "trademark right"},
      {"zh": "著作权", "en": "copyright"},
      {"zh": "商业秘密", "en": "trade secret"},
      {"zh": "侵权", "en": "infringement"}
    ],
    "abbreviations": {
      "民法典": "Civil Code",
      "刑法": "Criminal Law",
      "刑诉法": "Criminal Procedure Law",
      "民诉法": "Civil Procedure Law",
      "公司法": "Company Law",
      "劳动法": "Labor Law",
      "最高法": "Supreme People's Court",
      "最高检": "Supreme People's Procuratorate",
      "人大": "National People's Congress",
      "司法解释": "judicial interpretation"
    }
  },
  "translation_notes": [
    {"zh": "被告 vs 被告人", "note": "'被告' for civil/admin, '被告人' for criminal"},
    {"zh": "抵押 vs 质押", "note": "抵押 no transfer, 质押 with transfer of possession"},
    {"zh": "判决 vs 裁定", "note": "判决 for substance, 裁定 for procedure"},
    {"zh": "法定代表人 vs 法人代表", "note": "法定代表人 is statutory position"}
  ]
}
