{
  "metadata": {
    "language": "hi",
    "language_name": "Hindi",
    "glossary_type": "वित्तीय शब्दावली",
    "version": "1.0.0",
    "created": "2025-11-25",
    "description": "भारतीय वित्तीय प्रणाली की व्यापक शब्दावली",
    "sources": [
      "भारतीय रिज़र्व बैंक (RBI)",
      "भारतीय प्रतिभूति और विनिमय बोर्ड (SEBI)",
      "वित्त मंत्रालय भारत",
      "राष्ट्रीय स्टॉक एक्सचेंज (NSE)",
      "बॉम्बे स्टॉक एक्सचेंज (BSE)"
    ],
    "total_terms": 250
  },
  "categories": {
    "accounting": [
      {"hi": "परिसंपत्ति", "en": "Asset"},
      {"hi": "देयता", "en": "Liability"},
      {"hi": "इक्विटी", "en": "Equity"},
      {"hi": "राजस्व", "en": "Revenue"},
      {"hi": "व्यय", "en": "Expense"},
      {"hi": "मूल्यह्रास", "en": "Depreciation"},
      {"hi": "भारतीय लेखा मानक", "en": "Indian Accounting Standards"},
      {"hi": "अंतर्राष्ट्रीय वित्तीय रिपोर्टिंग मानक", "en": "IFRS"},
      {"hi": "चालू परिसम्पत्ति", "en": "Current Assets"},
      {"hi": "स्थिर परिसम्पत्ति", "en": "Fixed Assets"},
      {"hi": "अमूर्त परिसम्पत्ति", "en": "Intangible Assets"},
      {"hi": "चालू देयता", "en": "Current Liabilities"},
      {"hi": "दीर्घकालिक देयता", "en": "Long-term Liabilities"},
      {"hi": "प्राप्य खाते", "en": "Accounts Receivable"},
      {"hi": "देय खाते", "en": "Accounts Payable"},
      {"hi": "लाभांश", "en": "Dividend"},
      {"hi": "शुद्ध लाभ", "en": "Net Profit"},
      {"hi": "सकल लाभ", "en": "Gross Profit"}
    ],
    "banking": [
      {"hi": "भारतीय रिज़र्व बैंक", "en": "Reserve Bank of India"},
      {"hi": "रेपो दर", "en": "Repo Rate"},
      {"hi": "रिवर्स रेपो दर", "en": "Reverse Repo Rate"},
      {"hi": "बैंक दर", "en": "Bank Rate"},
      {"hi": "ब्याज दर", "en": "Interest Rate"},
      {"hi": "नकद आरक्षित अनुपात", "en": "Cash Reserve Ratio"},
      {"hi": "सांविधिक तरलता अनुपात", "en": "Statutory Liquidity Ratio"},
      {"hi": "ऋण", "en": "Loan"},
      {"hi": "संपार्श्विक", "en": "Collateral"},
      {"hi": "गृह ऋण", "en": "Home Loan"},
      {"hi": "व्यक्तिगत ऋण", "en": "Personal Loan"},
      {"hi": "कार्यशील पूंजी ऋण", "en": "Working Capital Loan"},
      {"hi": "ऋण रेटिंग", "en": "Credit Rating"},
      {"hi": "ऋण जोखिम", "en": "Credit Risk"},
      {"hi": "गैर-निष्पादित परिसंपत्ति", "en": "Non-Performing Asset"},
      {"hi": "NPA", "en": "Non-Performing Asset"},
      {"hi": "जमा खाता", "en": "Deposit Account"},
      {"hi": "बचत खाता", "en": "Savings Account"},
      {"hi": "चालू खाता", "en": "Current Account"},
      {"hi": "सावधि जमा", "en": "Fixed Deposit"},
      {"hi": "आवर्ती जमा", "en": "Recurring Deposit"},
      {"hi": "तरलता", "en": "Liquidity"},
      {"hi": "ओवरड्राफ्ट", "en": "Overdraft"},
      {"hi": "डेबिट कार्ड", "en": "Debit Card"},
      {"hi": "क्रेडिट कार्ड", "en": "Credit Card"},
      {"hi": "यूपीआई", "en": "UPI"}
    ],
    "investments": [
      {"hi": "शेयर", "en": "Share"},
      {"hi": "बांड", "en": "Bond"},
      {"hi": "डिबेंचर", "en": "Debenture"},
      {"hi": "म्यूचुअल फंड", "en": "Mutual Fund"},
      {"hi": "एक्सचेंज-ट्रेडेड फंड", "en": "ETF"},
      {"hi": "व्युत्पन्न", "en": "Derivative"},
      {"hi": "फ्यूचर्स", "en": "Futures"},
      {"hi": "ऑप्शन", "en": "Option"},
      {"hi": "कॉल ऑप्शन", "en": "Call Option"},
      {"hi": "पुट ऑप्शन", "en": "Put Option"},
      {"hi": "स्वैप", "en": "Swap"},
      {"hi": "पोर्टफोलियो", "en": "Portfolio"},
      {"hi": "विविधीकरण", "en": "Diversification"},
      {"hi": "परिसंपत्ति आवंटन", "en": "Asset Allocation"},
      {"hi": "जोखिम प्रबंधन", "en": "Risk Management"},
      {"hi": "हेज फंड", "en": "Hedge Fund"},
      {"hi": "निजी इक्विटी", "en": "Private Equity"},
      {"hi": "उद्यम पूंजी", "en": "Venture Capital"},
      {"hi": "रिटर्न", "en": "Return"},
      {"hi": "अपेक्षित रिटर्न", "en": "Expected Return"}
    ],
    "stock_market": [
      {"hi": "भारतीय प्रतिभूति और विनिमय बोर्ड", "en": "SEBI"},
      {"hi": "नेशनल स्टॉक एक्सचेंज", "en": "National Stock Exchange"},
      {"hi": "NSE", "en": "National Stock Exchange"},
      {"hi": "बॉम्बे स्टॉक एक्सचेंज", "en": "Bombay Stock Exchange"},
      {"hi": "BSE", "en": "Bombay Stock Exchange"},
      {"hi": "निफ्टी 50", "en": "NIFTY 50"},
      {"hi": "सेंसेक्स", "en": "SENSEX"},
      {"hi": "सूचकांक", "en": "Index"},
      {"hi": "बाजार पूंजीकरण", "en": "Market Capitalization"},
      {"hi": "प्रतिभूतियां", "en": "Securities"},
      {"hi": "व्यापार", "en": "Trading"},
      {"hi": "एक्सचेंज", "en": "Exchange"},
      {"hi": "स्टॉक ब्रोकर", "en": "Stock Broker"},
      {"hi": "डीमैट खाता", "en": "Demat Account"},
      {"hi": "ट्रेडिंग खाता", "en": "Trading Account"},
      {"hi": "बोली मूल्य", "en": "Bid Price"},
      {"hi": "पूछ मूल्य", "en": "Ask Price"},
      {"hi": "बाजार मूल्य", "en": "Market Price"},
      {"hi": "अंकित मूल्य", "en": "Face Value"},
      {"hi": "बाजार आदेश", "en": "Market Order"},
      {"hi": "सीमा आदेश", "en": "Limit Order"},
      {"hi": "स्टॉप-लॉस", "en": "Stop-Loss"},
      {"hi": "प्राथमिक बाजार", "en": "Primary Market"},
      {"hi": "द्वितीयक बाजार", "en": "Secondary Market"},
      {"hi": "पूंजी बाजार", "en": "Capital Market"},
      {"hi": "मुद्रा बाजार", "en": "Money Market"},
      {"hi": "तेजी का बाजार", "en": "Bull Market"},
      {"hi": "मंदी का बाजार", "en": "Bear Market"},
      {"hi": "मौलिक विश्लेषण", "en": "Fundamental Analysis"},
      {"hi": "तकनीकी विश्लेषण", "en": "Technical Analysis"},
      {"hi": "मूल्य-आय अनुपात", "en": "P/E Ratio"},
      {"hi": "बुक वैल्यू", "en": "Book Value"},
      {"hi": "प्रति शेयर आय", "en": "Earnings Per Share"},
      {"hi": "EPS", "en": "Earnings Per Share"}
    ],
    "corporate_finance": [
      {"hi": "आरंभिक सार्वजनिक प्रस्ताव", "en": "Initial Public Offering"},
      {"hi": "IPO", "en": "Initial Public Offering"},
      {"hi": "फॉलो-ऑन पब्लिक ऑफर", "en": "Follow-on Public Offer"},
      {"hi": "FPO", "en": "Follow-on Public Offer"},
      {"hi": "राइट्स इशू", "en": "Rights Issue"},
      {"hi": "बोनस शेयर", "en": "Bonus Shares"},
      {"hi": "ड्राफ्ट रेड हेरिंग प्रॉस्पेक्टस", "en": "DRHP"},
      {"hi": "प्राइस बैंड", "en": "Price Band"},
      {"hi": "सदस्यता", "en": "Subscription"},
      {"hi": "लिस्टिंग", "en": "Listing"},
      {"hi": "विलय", "en": "Merger"},
      {"hi": "अधिग्रहण", "en": "Acquisition"},
      {"hi": "विलय और अधिग्रहण", "en": "M&A"},
      {"hi": "उचित परिश्रम", "en": "Due Diligence"},
      {"hi": "मूल्यांकन", "en": "Valuation"},
      {"hi": "इक्विटी वित्तपोषण", "en": "Equity Financing"},
      {"hi": "ऋण वित्तपोषण", "en": "Debt Financing"},
      {"hi": "कार्यशील पूंजी", "en": "Working Capital"},
      {"hi": "पूंजीगत व्यय", "en": "Capital Expenditure"},
      {"hi": "परिचालन व्यय", "en": "Operating Expenditure"},
      {"hi": "नकदी प्रवाह", "en": "Cash Flow"},
      {"hi": "मुक्त नकदी प्रवाह", "en": "Free Cash Flow"},
      {"hi": "निदेशक मंडल", "en": "Board of Directors"},
      {"hi": "शेयरधारक", "en": "Shareholder"},
      {"hi": "हितधारक", "en": "Stakeholder"},
      {"hi": "कॉर्पोरेट प्रशासन", "en": "Corporate Governance"},
      {"hi": "वार्षिक आम बैठक", "en": "Annual General Meeting"},
      {"hi": "AGM", "en": "Annual General Meeting"}
    ],
    "financial_statements": [
      {"hi": "बैलेंस शीट", "en": "Balance Sheet"},
      {"hi": "आय विवरण", "en": "Income Statement"},
      {"hi": "लाभ-हानि खाता", "en": "Profit and Loss Account"},
      {"hi": "नकदी प्रवाह विवरण", "en": "Cash Flow Statement"},
      {"hi": "इक्विटी में परिवर्तन का विवरण", "en": "Statement of Changes in Equity"},
      {"hi": "परिचालन गतिविधियों से नकदी प्रवाह", "en": "Operating Cash Flow"},
      {"hi": "निवेश गतिविधियों से नकदी प्रवाह", "en": "Investing Cash Flow"},
      {"hi": "वित्तपोषण गतिविधियों से नकदी प्रवाह", "en": "Financing Cash Flow"}
    ],
    "financial_ratios": [
      {"hi": "तरलता अनुपात", "en": "Liquidity Ratio"},
      {"hi": "लाभप्रदता अनुपात", "en": "Profitability Ratio"},
      {"hi": "ऋण-इक्विटी अनुपात", "en": "Debt-to-Equity Ratio"},
      {"hi": "चालू अनुपात", "en": "Current Ratio"},
      {"hi": "त्वरित अनुपात", "en": "Quick Ratio"},
      {"hi": "परिसंपत्ति पर रिटर्न", "en": "Return on Assets"},
      {"hi": "ROA", "en": "Return on Assets"},
      {"hi": "इक्विटी पर रिटर्न", "en": "Return on Equity"},
      {"hi": "ROE", "en": "Return on Equity"},
      {"hi": "निवेश पर रिटर्न", "en": "Return on Investment"},
      {"hi": "ROI", "en": "Return on Investment"}
    ],
    "accounting_principles": [
      {"hi": "दोहरा लेखा प्रणाली", "en": "Double-Entry System"},
      {"hi": "उपार्जन लेखांकन", "en": "Accrual Accounting"},
      {"hi": "नकद आधार लेखांकन", "en": "Cash Basis Accounting"},
      {"hi": "लेखा अवधि", "en": "Accounting Period"},
      {"hi": "वित्तीय रिपोर्टिंग", "en": "Financial Reporting"},
      {"hi": "वित्तीय स्वास्थ्य", "en": "Financial Health"},
      {"hi": "वित्तीय प्रदर्शन", "en": "Financial Performance"},
      {"hi": "लेखा परीक्षा", "en": "Audit"},
      {"hi": "लेखा परीक्षक", "en": "Auditor"},
      {"hi": "वित्तीय वर्ष", "en": "Financial Year"},
      {"hi": "तिमाही परिणाम", "en": "Quarterly Results"},
      {"hi": "वार्षिक रिपोर्ट", "en": "Annual Report"}
    ],
    "abbreviations": {
      "RBI": "भारतीय रिज़र्व बैंक",
      "SEBI": "भारतीय प्रतिभूति और विनिमय बोर्ड",
      "NSE": "राष्ट्रीय स्टॉक एक्सचेंज",
      "BSE": "बॉम्बे स्टॉक एक्सचेंज",
      "IPO": "आरंभिक सार्वजनिक प्रस्ताव",
      "FPO": "फॉलो-ऑन पब्लिक ऑफर",
      "M&A": "विलय और अधिग्रहण",
      "EPS": "प्रति शेयर आय",
      "P/E": "मूल्य-आय अनुपात",
      "ROA": "परिसंपत्ति पर रिटर्न",
      "ROE": "इक्विटी पर रिटर्न",
      "ROI": "निवेश पर रिटर्न",
      "AGM": "वार्षिक आम बैठक",
      "NPA": "गैर-निष्पादित परिसंपत्ति",
      "UPI": "एकीकृत भुगतान इंटरफेस",
      "CRR": "नकद आरक्षित अनुपात",
      "SLR": "सांविधिक तरलता अनुपात"
    }
  }
}
